pyrules/__init__.py
pyrules/engine.py
pyrules/memory.py
pyrules/pyrules.py
pyrules/rules.py
pyrules-0.1.0.dist-info/DESCRIPTION.rst
pyrules-0.1.0.dist-info/METADATA
pyrules-0.1.0.dist-info/RECORD
pyrules-0.1.0.dist-info/WHEEL
pyrules-0.1.0.dist-info/metadata.json
pyrules-0.1.0.dist-info/top_level.txt
