Metadata-Version: 2.0
Name: pyrules
Version: 0.1.0
Summary: A Python rules engine inspired by OPS5.
Home-page: https://github.com/petrilli/pyrules
Author: Christopher Petrilli
Author-email: petrilli@amber.org
License: BSD license
Keywords: pyrules
Platform: UNKNOWN
Classifier: Development Status :: 2 - Pre-Alpha
Classifier: Intended Audience :: Developers
Classifier: License :: OSI Approved :: BSD License
Classifier: Natural Language :: English
Classifier: Programming Language :: Python :: 2
Classifier: Programming Language :: Python :: 2.7
Requires-Dist: attrs (~=17.0)
